pythermocalcdb_nasa/__init__.py
pythermocalcdb_nasa/app.py
pythermocalcdb_nasa/configs/__init__.py
pythermocalcdb_nasa/configs/constants.py
pythermocalcdb_nasa/configs/info.py
pythermocalcdb_nasa/core/__init__.py
pythermocalcdb_nasa/core/hsg.py
pythermocalcdb_nasa/core/hsgs.py
pythermocalcdb_nasa/docs/__init__.py
pythermocalcdb_nasa/docs/rxn_adapter.py
pythermocalcdb_nasa/models/__init__.py
pythermocalcdb_nasa/thermo/__init__.py
pythermocalcdb_nasa/thermo/extractor.py
pythermocalcdb_nasa/utils/__init__.py
pythermocalcdb_nasa/utils/tools.py
pythermocalcdb_nasa-0.1.1.dist-info/licenses/LICENSE
pythermocalcdb_nasa-0.1.1.dist-info/METADATA
pythermocalcdb_nasa-0.1.1.dist-info/WHEEL
pythermocalcdb_nasa-0.1.1.dist-info/top_level.txt
pythermocalcdb_nasa-0.1.1.dist-info/RECORD
