Metadata-Version: 2.4
Name: pythermocalcdb-nasa
Version: 0.1.1
Summary: A NASA-polynomial thermochemistry engine for reaction and equilibrium calculations.
Author-email: Sina Gilassi <sina.gilassi@gmail.com>
License-Expression: Apache-2.0
Project-URL: Homepage, https://github.com/sinagilassi/PyThermoCalcDB-NASA
Project-URL: Source, https://github.com/sinagilassi/PyThermoCalcDB-NASA
Project-URL: Tracker, https://github.com/sinagilassi/PyThermoCalcDB-NASA/issues
Keywords: chemical-engineering,thermodynamics,thermodynamic-equations,thermodynamic-properties,process-simulation
Classifier: Development Status :: 1 - Planning
Classifier: Intended Audience :: Education
Classifier: Programming Language :: Python :: 3.11
Classifier: Operating System :: Unix
Classifier: Operating System :: MacOS :: MacOS X
Classifier: Operating System :: Microsoft :: Windows
Requires-Python: >=3.11
License-File: LICENSE
Requires-Dist: pycuc>=2.4.0
Requires-Dist: rich>=14.2.0
Requires-Dist: pythermocalcdb>=0.7.7
Requires-Dist: pythermodb>=1.12.2
Requires-Dist: pythermodb-settings>=0.2.3
Requires-Dist: pythermolinkdb>=1.4.9
Requires-Dist: pyreactlab-core>=0.1.3
Dynamic: license-file
